v3io_frames/__init__.py
v3io_frames/client.py
v3io_frames/dtypes.py
v3io_frames/errors.py
v3io_frames/frames_pb2.py
v3io_frames/frames_pb2_grpc.py
v3io_frames/grpc.py
v3io_frames/http.py
v3io_frames/pbutils.py
v3io_frames/pdutils.py
v3io_frames-0.13.13.dist-info/licenses/LICENSE.txt
v3io_frames-0.13.13.dist-info/METADATA
v3io_frames-0.13.13.dist-info/WHEEL
v3io_frames-0.13.13.dist-info/top_level.txt
v3io_frames-0.13.13.dist-info/RECORD
