Metadata-Version: 2.4
Name: v3io_frames
Version: 0.13.13
Summary: Unified multi-module DataFrames client for the Iguazio Data Science Platform
Home-page: https://github.com/v3io/frames
Author: Miki Tebeka
Author-email: miki@353solutions.com
License: MIT
Classifier: Development Status :: 4 - Beta
Classifier: Intended Audience :: Developers
Classifier: License :: OSI Approved :: Apache Software License
Classifier: Operating System :: POSIX :: Linux
Classifier: Operating System :: Microsoft :: Windows
Classifier: Operating System :: MacOS
Classifier: Programming Language :: Python :: 2
Classifier: Programming Language :: Python :: 2.7
Classifier: Programming Language :: Python :: 3
Classifier: Programming Language :: Python :: 3.6
Classifier: Programming Language :: Python :: 3.7
Classifier: Programming Language :: Python
Classifier: Topic :: Software Development :: Libraries :: Python Modules
Classifier: Topic :: Software Development :: Libraries
License-File: LICENSE.txt
Requires-Dist: googleapis-common-protos>=1.5.3
Requires-Dist: grpcio-tools>=1.49
Requires-Dist: protobuf<7,>=4
Requires-Dist: pandas>=0.23.4
Requires-Dist: requests>=2.19.1
Dynamic: author
Dynamic: author-email
Dynamic: classifier
Dynamic: description
Dynamic: description-content-type
Dynamic: home-page
Dynamic: license
Dynamic: license-file
Dynamic: requires-dist
Dynamic: summary
